whispercpy/__init__.py
whispercpy/constant.py
whispercpy/core.py
whispercpy/interface.py
whispercpy/stream.py
whispercpy/structs.py
whispercpy/utils.py
whispercpy-0.1.0.dist-info/licenses/LICENSE
whispercpy-0.1.0.dist-info/METADATA
whispercpy-0.1.0.dist-info/WHEEL
whispercpy-0.1.0.dist-info/top_level.txt
whispercpy-0.1.0.dist-info/RECORD
