Metadata-Version: 2.4
Name: whispercpy
Version: 0.1.0
Summary: Python wrapper for Whisper.cpp
Home-page: https://github.com/fann1993814/whisper.cpy
Author: Jason Fan
Author-email: Jason Fan <fann1993814@gmail.com>
License: MIT
Keywords: speech recognition,speech to text,STT,ASR,NLP
Classifier: Intended Audience :: Developers
Classifier: Operating System :: OS Independent
Classifier: Programming Language :: Python
Classifier: Programming Language :: Python :: 3
Classifier: Topic :: Multimedia
Classifier: Topic :: Multimedia :: Sound/Audio
Classifier: Topic :: Multimedia :: Sound/Audio :: Speech
Requires-Python: >=3.8
License-File: LICENSE
Requires-Dist: numpy>=1.25
Requires-Dist: scipy>=1.13.0
Requires-Dist: sounddevice>=0.5.0
Dynamic: author
Dynamic: home-page
Dynamic: license-file
Dynamic: requires-python
